mySimpleLogger/__init__.py
mySimpleLogger/simpleLogger.py
mySimpleLogger-0.0.1.dist-info/METADATA
mySimpleLogger-0.0.1.dist-info/WHEEL
mySimpleLogger-0.0.1.dist-info/top_level.txt
mySimpleLogger-0.0.1.dist-info/RECORD
