Metadata-Version: 2.1
Name: mySimpleLogger
Version: 0.0.1
Summary: simple logger wrapper
Home-page: https://github.com/iamgd67/myPySimpleLogger
Author: 67
Author-email: 67@gd67.com
License: UNKNOWN
Project-URL: Bug Tracker, https://github.com/iamgd67/myPySimpleLogger/issues
Platform: UNKNOWN
Classifier: Programming Language :: Python :: 3
Classifier: Operating System :: OS Independent
Requires-Python: >=3.6
